my_package/__init__.py
my_package/model.py
my_package/analysis/__init__.py
my_package/analysis/visualize.py
my_package/data/__init__.py
my_package/data/dataset.py
my_package/data/transforms/__init__.py
my_package/data/transforms/blur.py
my_package/data/transforms/crop.py
my_package/data/transforms/flip.py
my_package/data/transforms/rescale.py
my_package/data/transforms/rotate.py
19CS30055_package-0.0.6.dist-info/METADATA
19CS30055_package-0.0.6.dist-info/WHEEL
19CS30055_package-0.0.6.dist-info/top_level.txt
19CS30055_package-0.0.6.dist-info/RECORD
